LICENSE
MANIFEST.in
README.md
install_script.py
setup.py
kdui2py/__init__.py
kdui2py/fileutil.py
kdui2py/kdui2py.py
kdui2py/kdui2py_ui.py
kdui2py/logo.jpg
kdui2py.egg-info/PKG-INFO
kdui2py.egg-info/SOURCES.txt
kdui2py.egg-info/dependency_links.txt
kdui2py.egg-info/entry_points.txt
kdui2py.egg-info/not-zip-safe
kdui2py.egg-info/requires.txt
kdui2py.egg-info/top_level.txt